pythaitts/__init__.py
pythaitts/preprocess.py
pythaitts/pretrained/__init__.py
pythaitts/pretrained/khanomtan_tts.py
pythaitts/pretrained/lunarlist_model.py
pythaitts/pretrained/lunarlist_onnx.py
pythaitts/pretrained/vachana_tts.py
pythaitts-0.4.2.dist-info/licenses/LICENSE
tests/__init__.py
tests/test_preprocess.py
tests/test_vachana.py
pythaitts-0.4.2.dist-info/METADATA
pythaitts-0.4.2.dist-info/WHEEL
pythaitts-0.4.2.dist-info/top_level.txt
pythaitts-0.4.2.dist-info/RECORD
