Metadata-Version: 2.4
Name: PyThaiTTS
Version: 0.4.2
Summary: Open Source Thai Text-to-speech library in Python
Home-page: https://github.com/pythainlp/pythaitts
Author: Wannaphong
Author-email: wannaphong@yahoo.com
License: Apache Software License 2.0
Project-URL: Documentation, https://github.com/pythainlp/pythaitts
Project-URL: Source, https://github.com/pythainlp/pythaitts
Project-URL: Bug Reports, https://github.com/pythainlp/pythaitts/issues
Keywords: Thai,NLP,natural language processing,text analytics,text processing,localization,computational linguistics,text-to-speech
Classifier: Development Status :: 3 - Alpha
Classifier: Programming Language :: Python :: 3
Classifier: Intended Audience :: Developers
Classifier: License :: OSI Approved :: Apache Software License
Classifier: Topic :: Scientific/Engineering :: Artificial Intelligence
Classifier: Topic :: Text Processing
Classifier: Topic :: Text Processing :: General
Classifier: Topic :: Text Processing :: Linguistic
Requires-Python: >=3.6
License-File: LICENSE
Requires-Dist: huggingface_hub
Requires-Dist: numpy>=1.22
Requires-Dist: onnxruntime
Requires-Dist: vachanatts
Requires-Dist: soundfile
Dynamic: author
Dynamic: author-email
Dynamic: classifier
Dynamic: description
Dynamic: description-content-type
Dynamic: home-page
Dynamic: keywords
Dynamic: license
Dynamic: license-file
Dynamic: project-url
Dynamic: requires-dist
Dynamic: requires-python
Dynamic: summary
